tradezero/__init__.py
tradezero-0.1.0.dist-info/METADATA
tradezero-0.1.0.dist-info/WHEEL
tradezero-0.1.0.dist-info/RECORD
